scVAEIT/VAEIT.py
scVAEIT/__about__.py
scVAEIT/__init__.py
scVAEIT/model.py
scVAEIT/nn_utils.py
scVAEIT/train.py
scVAEIT/utils.py
scvaeit-1.1.1.dist-info/METADATA
scvaeit-1.1.1.dist-info/WHEEL
scvaeit-1.1.1.dist-info/licenses/LICENSE
scvaeit-1.1.1.dist-info/RECORD
