Metadata-Version: 2.4
Name: scVAEIT
Version: 1.1.1
Summary: scVAEIT is a Python module of Variational autoencoder for single-cell mosaic integration and transfer learning.
Maintainer-email: Jin-Hong Du <jinhongd@andrew.cmu.com>
License: MIT License
License-File: LICENSE
Classifier: Intended Audience :: Developers
Classifier: License :: OSI Approved :: MIT License
Classifier: Programming Language :: Python :: 3
Requires-Python: >=3.9
Requires-Dist: jupyter
Requires-Dist: matplotlib
Requires-Dist: numpy
Requires-Dist: pandas
Requires-Dist: scanpy>=1.9.2
Requires-Dist: scikit-learn
Requires-Dist: tensorflow-probability<0.24,>=0.12
Requires-Dist: tensorflow<2.16,>=2.12
